WiSync/Color.py
WiSync/Cursors.py
WiSync/Dimensions.py
WiSync/Drawer.py
WiSync/Font.py
WiSync/Ider.py
WiSync/Printer.py
WiSync/Style.py
WiSync/Time.py
WiSync/UI.py
WiSync/__init__.py
WiSync-1.0.0.dev1.dist-info/DESCRIPTION.rst
WiSync-1.0.0.dev1.dist-info/METADATA
WiSync-1.0.0.dev1.dist-info/RECORD
WiSync-1.0.0.dev1.dist-info/WHEEL
WiSync-1.0.0.dev1.dist-info/metadata.json
WiSync-1.0.0.dev1.dist-info/top_level.txt
