Metadata-Version: 2.0
Name: WiSync
Version: 1.0.0.dev1
Summary: You favorite home automation platform.
Home-page: https://github.com/CMakerA/WiSync
Author: ArnyminerZ
Author-email: arnyminer.z@gmail.com
License: MIT
Platform: UNKNOWN
Requires-Python: >=3
Requires-Dist: pygame
